{
  "lists": [
    {
      "id": 1,
      "name": "Сделать что то интересное",
      "colorId": 5
    },
    {
      "id": 2,
      "name": "Фронтенд app test",
      "colorId": 4
    },
    {
      "id": 3,
      "name": "Фильмы и сериалы",
      "colorId": 3
    },
    {
      "id": 8779767,
      "name": "Second app",
      "colorId": 5
    },
    {
      "id": 6015825,
      "name": "Tesp app",
      "colorId": 1
    }
  ],
  "tasks": [
    {
      "id": 4,
      "listId": 2,
      "text": "Redux (redux-observable, redux-saga)",
      "completed": true
    },
    {
      "id": 12,
      "text": "Study Vuex/Pinia",
      "completed": true,
      "listId": 2
    },
    {
      "id": 8425994,
      "completed": true,
      "listId": 8779767,
      "text": "Test app"
    },
    {
      "id": 5340503,
      "text": "My beautiful app",
      "completed": true,
      "listId": 8779767
    },
    {
      "id": 1163316,
      "text": "Таск 2",
      "completed": true,
      "listId": 1
    },
    {
      "id": 1660306,
      "completed": false,
      "listId": 6015825,
      "text": "My test app"
    },
    {
      "id": 3775095,
      "completed": true,
      "listId": 6015825,
      "text": "Second test app"
    },
    {
      "id": 9186765,
      "completed": true,
      "listId": 6015825,
      "text": "My third app"
    }
  ],
  "colors": [
    {
      "id": 1,
      "hex": "#C9D1D3",
      "name": "grey"
    },
    {
      "id": 2,
      "hex": "#42B883",
      "name": "green"
    },
    {
      "id": 3,
      "hex": "#64C4ED",
      "name": "blue"
    },
    {
      "id": 4,
      "hex": "#FFBBCC",
      "name": "pink"
    },
    {
      "id": 5,
      "hex": "#B6E6BD",
      "name": "lime"
    },
    {
      "id": 6,
      "hex": "#C355F5",
      "name": "purple"
    },
    {
      "id": 7,
      "hex": "#110133",
      "name": "black"
    },
    {
      "id": 8,
      "hex": "#FF6464",
      "name": "red"
    }
  ]
}